reciprocity/__init__.py
reciprocity/apps.py
reciprocity/core.py
reciprocity/tests.py
reciprocity/static/reciprocity/html/callout-with-link.html
reciprocity/static/reciprocity/html/callout.html
reciprocity/static/reciprocity/html/modal-dialog.html
reciprocity/static/reciprocity/html/please-wait-dialog.html
reciprocity/static/reciprocity/html/progress-dialog.html
reciprocity/static/reciprocity/js/jquery.loadTemplate.js
reciprocity/static/reciprocity/js/reciprocity.js
reciprocity/static/reciprocity/js/tests/.DS_Store
reciprocity/static/reciprocity/js/tests/package.json
reciprocity/static/reciprocity/js/tests/yarn.lock
reciprocity/static/reciprocity/js/tests/test/index.html
reciprocity/static/reciprocity/js/tests/test/reciprocity.test.js
reciprocity/templates/reciprocity/body.html
reciprocity/templates/reciprocity/header.html
django_reciprocity-0.0.1.dist-info/LICENSE
django_reciprocity-0.0.1.dist-info/METADATA
django_reciprocity-0.0.1.dist-info/WHEEL
django_reciprocity-0.0.1.dist-info/top_level.txt
django_reciprocity-0.0.1.dist-info/RECORD
