Metadata-Version: 2.1
Name: django-reciprocity
Version: 0.0.1
Summary: Interactive web apps with Django
Home-page: https://github.com/mpasternak/django-reciprocity
Author: Michał Pasternak
Author-email: michal.dtz@gmail.com
License: MIT license
Platform: UNKNOWN
Classifier: Development Status :: 2 - Pre-Alpha
Classifier: Intended Audience :: Developers
Classifier: License :: OSI Approved :: MIT License
Classifier: Natural Language :: English
Classifier: Programming Language :: Python :: 3.7
Requires-Dist: Django
